<Spawns>
  <Points>
    <Name>PrismOfLight#20</Name>
    <UniqueId>9e47ba43-d83d-4a3f-a496-2745f9406c6f</UniqueId>
    <Map>Felucca</Map>
    <X>6502</X>
    <Y>163</Y>
    <Width>16</Width>
    <Height>16</Height>
    <CentreX>6510</CentreX>
    <CentreY>171</CentreY>
    <CentreZ>0</CentreZ>
    <Range>8</Range>
    <MaxCount>3</MaxCount>
    <MinDelay>5</MinDelay>
    <MaxDelay>10</MaxDelay>
    <DelayInSec>False</DelayInSec>
    <Duration>0</Duration>
    <DespawnTime>0</DespawnTime>
    <ProximityRange>-1</ProximityRange>
    <ProximityTriggerSound>500</ProximityTriggerSound>
    <TriggerProbability>1</TriggerProbability>
    <InContainer>False</InContainer>
    <MinRefractory>0</MinRefractory>
    <MaxRefractory>0</MaxRefractory>
    <TODStart>0</TODStart>
    <TODEnd>0</TODEnd>
    <TODMode>0</TODMode>
    <KillReset>1</KillReset>
    <ExternalTriggering>False</ExternalTriggering>
    <SequentialSpawning>-1</SequentialSpawning>
    <AllowGhostTriggering>False</AllowGhostTriggering>
    <AllowNPCTriggering>False</AllowNPCTriggering>
    <SpawnOnTrigger>False</SpawnOnTrigger>
    <SmartSpawning>False</SmartSpawning>
    <Team>0</Team>
    <Amount>1</Amount>
    <IsGroup>False</IsGroup>
    <IsRunning>True</IsRunning>
    <IsHomeRangeRelative>False</IsHomeRangeRelative>
    <Objects2>protector:MX=3:SB=0:RT=0:TO=0:KL=0:RK=0:CA=1:DN=-1:DX=-1:SP=1:PR=-1</Objects2>
  </Points>
  <Points>
    <Name>PrismOfLight#19</Name>
    <UniqueId>0b003d62-d12f-4df6-8cd3-04d879730344</UniqueId>
    <Map>Felucca</Map>
    <X>6573</X>
    <Y>178</Y>
    <Width>10</Width>
    <Height>10</Height>
    <CentreX>6578</CentreX>
    <CentreY>183</CentreY>
    <CentreZ>31</CentreZ>
    <Range>5</Range>
    <MaxCount>2</MaxCount>
    <MinDelay>5</MinDelay>
    <MaxDelay>10</MaxDelay>
    <DelayInSec>False</DelayInSec>
    <Duration>0</Duration>
    <DespawnTime>0</DespawnTime>
    <ProximityRange>-1</ProximityRange>
    <ProximityTriggerSound>500</ProximityTriggerSound>
    <TriggerProbability>1</TriggerProbability>
    <InContainer>False</InContainer>
    <MinRefractory>0</MinRefractory>
    <MaxRefractory>0</MaxRefractory>
    <TODStart>0</TODStart>
    <TODEnd>0</TODEnd>
    <TODMode>0</TODMode>
    <KillReset>1</KillReset>
    <ExternalTriggering>False</ExternalTriggering>
    <SequentialSpawning>-1</SequentialSpawning>
    <AllowGhostTriggering>False</AllowGhostTriggering>
    <AllowNPCTriggering>False</AllowNPCTriggering>
    <SpawnOnTrigger>False</SpawnOnTrigger>
    <SmartSpawning>False</SmartSpawning>
    <Team>0</Team>
    <Amount>1</Amount>
    <IsGroup>False</IsGroup>
    <IsRunning>True</IsRunning>
    <IsHomeRangeRelative>False</IsHomeRangeRelative>
    <Objects2>Ferret:MX=2:SB=0:RT=0:TO=0:KL=0:RK=0:CA=1:DN=-1:DX=-1:SP=1:PR=-1</Objects2>
  </Points>
  <Points>
    <Name>PrismOfLight#18</Name>
    <UniqueId>a78d4aac-755e-408f-82a4-ed15274c9949</UniqueId>
    <Map>Felucca</Map>
    <X>6528</X>
    <Y>75</Y>
    <Width>8</Width>
    <Height>8</Height>
    <CentreX>6532</CentreX>
    <CentreY>79</CentreY>
    <CentreZ>-10</CentreZ>
    <Range>4</Range>
    <MaxCount>1</MaxCount>
    <MinDelay>5</MinDelay>
    <MaxDelay>10</MaxDelay>
    <DelayInSec>False</DelayInSec>
    <Duration>0</Duration>
    <DespawnTime>0</DespawnTime>
    <ProximityRange>-1</ProximityRange>
    <ProximityTriggerSound>500</ProximityTriggerSound>
    <TriggerProbability>1</TriggerProbability>
    <InContainer>False</InContainer>
    <MinRefractory>0</MinRefractory>
    <MaxRefractory>0</MaxRefractory>
    <TODStart>0</TODStart>
    <TODEnd>0</TODEnd>
    <TODMode>0</TODMode>
    <KillReset>1</KillReset>
    <ExternalTriggering>False</ExternalTriggering>
    <SequentialSpawning>-1</SequentialSpawning>
    <AllowGhostTriggering>False</AllowGhostTriggering>
    <AllowNPCTriggering>False</AllowNPCTriggering>
    <SpawnOnTrigger>False</SpawnOnTrigger>
    <SmartSpawning>False</SmartSpawning>
    <Team>0</Team>
    <Amount>1</Amount>
    <IsGroup>False</IsGroup>
    <IsRunning>True</IsRunning>
    <IsHomeRangeRelative>False</IsHomeRangeRelative>
    <Objects2>CrystalDaemon:MX=1:SB=0:RT=0:TO=0:KL=0:RK=0:CA=1:DN=-1:DX=-1:SP=1:PR=-1</Objects2>
  </Points>
  <Points>
    <Name>PrismOfLight#17</Name>
    <UniqueId>e85317b5-786a-492e-8151-e2c84593c757</UniqueId>
    <Map>Felucca</Map>
    <X>6502</X>
    <Y>146</Y>
    <Width>10</Width>
    <Height>10</Height>
    <CentreX>6507</CentreX>
    <CentreY>151</CentreY>
    <CentreZ>0</CentreZ>
    <Range>5</Range>
    <MaxCount>3</MaxCount>
    <MinDelay>5</MinDelay>
    <MaxDelay>10</MaxDelay>
    <DelayInSec>False</DelayInSec>
    <Duration>0</Duration>
    <DespawnTime>0</DespawnTime>
    <ProximityRange>-1</ProximityRange>
    <ProximityTriggerSound>500</ProximityTriggerSound>
    <TriggerProbability>1</TriggerProbability>
    <InContainer>False</InContainer>
    <MinRefractory>0</MinRefractory>
    <MaxRefractory>0</MaxRefractory>
    <TODStart>0</TODStart>
    <TODEnd>0</TODEnd>
    <TODMode>0</TODMode>
    <KillReset>1</KillReset>
    <ExternalTriggering>False</ExternalTriggering>
    <SequentialSpawning>-1</SequentialSpawning>
    <AllowGhostTriggering>False</AllowGhostTriggering>
    <AllowNPCTriggering>False</AllowNPCTriggering>
    <SpawnOnTrigger>False</SpawnOnTrigger>
    <SmartSpawning>False</SmartSpawning>
    <Team>0</Team>
    <Amount>1</Amount>
    <IsGroup>False</IsGroup>
    <IsRunning>True</IsRunning>
    <IsHomeRangeRelative>False</IsHomeRangeRelative>
    <Objects2>protector:MX=3:SB=0:RT=0:TO=0:KL=0:RK=0:CA=1:DN=-1:DX=-1:SP=1:PR=-1</Objects2>
  </Points>
  <Points>
    <Name>PrismOfLight#16</Name>
    <UniqueId>ec31f05c-6742-441a-99ae-a2fa0b97b4b6</UniqueId>
    <Map>Felucca</Map>
    <X>6502</X>
    <Y>120</Y>
    <Width>0</Width>
    <Height>0</Height>
    <CentreX>6502</CentreX>
    <CentreY>120</CentreY>
    <CentreZ>-10</CentreZ>
    <Range>0</Range>
    <MaxCount>1</MaxCount>
    <MinDelay>5</MinDelay>
    <MaxDelay>10</MaxDelay>
    <DelayInSec>False</DelayInSec>
    <Duration>0</Duration>
    <DespawnTime>0</DespawnTime>
    <ProximityRange>-1</ProximityRange>
    <ProximityTriggerSound>500</ProximityTriggerSound>
    <TriggerProbability>1</TriggerProbability>
    <InContainer>False</InContainer>
    <MinRefractory>0</MinRefractory>
    <MaxRefractory>0</MaxRefractory>
    <TODStart>0</TODStart>
    <TODEnd>0</TODEnd>
    <TODMode>0</TODMode>
    <KillReset>1</KillReset>
    <ExternalTriggering>False</ExternalTriggering>
    <SequentialSpawning>-1</SequentialSpawning>
    <AllowGhostTriggering>False</AllowGhostTriggering>
    <AllowNPCTriggering>False</AllowNPCTriggering>
    <SpawnOnTrigger>False</SpawnOnTrigger>
    <SmartSpawning>False</SmartSpawning>
    <Team>0</Team>
    <Amount>1</Amount>
    <IsGroup>False</IsGroup>
    <IsRunning>True</IsRunning>
    <IsHomeRangeRelative>False</IsHomeRangeRelative>
    <Objects2>treasurelevel3:MX=1:SB=0:RT=0:TO=0:KL=0:RK=0:CA=1:DN=-1:DX=-1:SP=1:PR=-1</Objects2>
  </Points>
  <Points>
    <Name>PrismOfLight#15</Name>
    <UniqueId>5a83e8e5-fe81-4a40-9e17-7e46b24a410a</UniqueId>
    <Map>Felucca</Map>
    <X>6520</X>
    <Y>164</Y>
    <Width>30</Width>
    <Height>30</Height>
    <CentreX>6535</CentreX>
    <CentreY>179</CentreY>
    <CentreZ>0</CentreZ>
    <Range>15</Range>
    <MaxCount>6</MaxCount>
    <MinDelay>5</MinDelay>
    <MaxDelay>10</MaxDelay>
    <DelayInSec>False</DelayInSec>
    <Duration>0</Duration>
    <DespawnTime>0</DespawnTime>
    <ProximityRange>-1</ProximityRange>
    <ProximityTriggerSound>500</ProximityTriggerSound>
    <TriggerProbability>1</TriggerProbability>
    <InContainer>False</InContainer>
    <MinRefractory>0</MinRefractory>
    <MaxRefractory>0</MaxRefractory>
    <TODStart>0</TODStart>
    <TODEnd>0</TODEnd>
    <TODMode>0</TODMode>
    <KillReset>1</KillReset>
    <ExternalTriggering>False</ExternalTriggering>
    <SequentialSpawning>-1</SequentialSpawning>
    <AllowGhostTriggering>False</AllowGhostTriggering>
    <AllowNPCTriggering>False</AllowNPCTriggering>
    <SpawnOnTrigger>False</SpawnOnTrigger>
    <SmartSpawning>False</SmartSpawning>
    <Team>0</Team>
    <Amount>1</Amount>
    <IsGroup>False</IsGroup>
    <IsRunning>True</IsRunning>
    <IsHomeRangeRelative>False</IsHomeRangeRelative>
    <Objects2>CrystalWisp:MX=5:SB=0:RT=0:TO=0:KL=0:RK=0:CA=1:DN=-1:DX=-1:SP=1:PR=-1:OBJ=CrystalLatticeSeeker:MX=5:SB=0:RT=0:TO=0:KL=0:RK=0:CA=1:DN=-1:DX=-1:SP=1:PR=-1:OBJ=treasurelevel2:MX=5:SB=0:RT=0:TO=0:KL=0:RK=0:CA=1:DN=-1:DX=-1:SP=1:PR=-1</Objects2>
  </Points>
  <Points>
    <Name>PrismOfLight#14</Name>
    <UniqueId>4660fc9b-b42d-43e5-b22f-1488020bc6e9</UniqueId>
    <Map>Felucca</Map>
    <X>6530</X>
    <Y>174</Y>
    <Width>8</Width>
    <Height>8</Height>
    <CentreX>6534</CentreX>
    <CentreY>178</CentreY>
    <CentreZ>0</CentreZ>
    <Range>4</Range>
    <MaxCount>2</MaxCount>
    <MinDelay>5</MinDelay>
    <MaxDelay>10</MaxDelay>
    <DelayInSec>False</DelayInSec>
    <Duration>0</Duration>
    <DespawnTime>0</DespawnTime>
    <ProximityRange>-1</ProximityRange>
    <ProximityTriggerSound>500</ProximityTriggerSound>
    <TriggerProbability>1</TriggerProbability>
    <InContainer>False</InContainer>
    <MinRefractory>0</MinRefractory>
    <MaxRefractory>0</MaxRefractory>
    <TODStart>0</TODStart>
    <TODEnd>0</TODEnd>
    <TODMode>0</TODMode>
    <KillReset>1</KillReset>
    <ExternalTriggering>False</ExternalTriggering>
    <SequentialSpawning>-1</SequentialSpawning>
    <AllowGhostTriggering>False</AllowGhostTriggering>
    <AllowNPCTriggering>False</AllowNPCTriggering>
    <SpawnOnTrigger>False</SpawnOnTrigger>
    <SmartSpawning>False</SmartSpawning>
    <Team>0</Team>
    <Amount>1</Amount>
    <IsGroup>False</IsGroup>
    <IsRunning>True</IsRunning>
    <IsHomeRangeRelative>False</IsHomeRangeRelative>
    <Objects2>CrystalWisp:MX=2:SB=0:RT=0:TO=0:KL=0:RK=0:CA=1:DN=-1:DX=-1:SP=1:PR=-1</Objects2>
  </Points>
  <Points>
    <Name>PrismOfLight#13</Name>
    <UniqueId>fbe7d389-4c0e-4eb6-ab2c-7c116df736d7</UniqueId>
    <Map>Felucca</Map>
    <X>6551</X>
    <Y>105</Y>
    <Width>30</Width>
    <Height>30</Height>
    <CentreX>6566</CentreX>
    <CentreY>120</CentreY>
    <CentreZ>0</CentreZ>
    <Range>15</Range>
    <MaxCount>7</MaxCount>
    <MinDelay>5</MinDelay>
    <MaxDelay>10</MaxDelay>
    <DelayInSec>False</DelayInSec>
    <Duration>0</Duration>
    <DespawnTime>0</DespawnTime>
    <ProximityRange>-1</ProximityRange>
    <ProximityTriggerSound>500</ProximityTriggerSound>
    <TriggerProbability>1</TriggerProbability>
    <InContainer>False</InContainer>
    <MinRefractory>0</MinRefractory>
    <MaxRefractory>0</MaxRefractory>
    <TODStart>0</TODStart>
    <TODEnd>0</TODEnd>
    <TODMode>0</TODMode>
    <KillReset>1</KillReset>
    <ExternalTriggering>False</ExternalTriggering>
    <SequentialSpawning>-1</SequentialSpawning>
    <AllowGhostTriggering>False</AllowGhostTriggering>
    <AllowNPCTriggering>False</AllowNPCTriggering>
    <SpawnOnTrigger>False</SpawnOnTrigger>
    <SmartSpawning>False</SmartSpawning>
    <Team>0</Team>
    <Amount>1</Amount>
    <IsGroup>False</IsGroup>
    <IsRunning>True</IsRunning>
    <IsHomeRangeRelative>False</IsHomeRangeRelative>
    <Objects2>Crystalvortex:MX=7:SB=0:RT=0:TO=0:KL=0:RK=0:CA=1:DN=-1:DX=-1:SP=1:PR=-1:OBJ=iceelemental:MX=7:SB=0:RT=0:TO=0:KL=0:RK=0:CA=1:DN=-1:DX=-1:SP=1:PR=-1</Objects2>
  </Points>
  <Points>
    <Name>PrismOfLight#12</Name>
    <UniqueId>807d69b6-1605-47b3-aeae-022977b119b2</UniqueId>
    <Map>Felucca</Map>
    <X>6468</X>
    <Y>164</Y>
    <Width>20</Width>
    <Height>20</Height>
    <CentreX>6478</CentreX>
    <CentreY>174</CentreY>
    <CentreZ>4</CentreZ>
    <Range>10</Range>
    <MaxCount>6</MaxCount>
    <MinDelay>5</MinDelay>
    <MaxDelay>10</MaxDelay>
    <DelayInSec>False</DelayInSec>
    <Duration>0</Duration>
    <DespawnTime>0</DespawnTime>
    <ProximityRange>-1</ProximityRange>
    <ProximityTriggerSound>500</ProximityTriggerSound>
    <TriggerProbability>1</TriggerProbability>
    <InContainer>False</InContainer>
    <MinRefractory>0</MinRefractory>
    <MaxRefractory>0</MaxRefractory>
    <TODStart>0</TODStart>
    <TODEnd>0</TODEnd>
    <TODMode>0</TODMode>
    <KillReset>1</KillReset>
    <ExternalTriggering>False</ExternalTriggering>
    <SequentialSpawning>-1</SequentialSpawning>
    <AllowGhostTriggering>False</AllowGhostTriggering>
    <AllowNPCTriggering>False</AllowNPCTriggering>
    <SpawnOnTrigger>False</SpawnOnTrigger>
    <SmartSpawning>False</SmartSpawning>
    <Team>0</Team>
    <Amount>1</Amount>
    <IsGroup>False</IsGroup>
    <IsRunning>True</IsRunning>
    <IsHomeRangeRelative>False</IsHomeRangeRelative>
    <Objects2>wisp:MX=6:SB=0:RT=0:TO=0:KL=0:RK=0:CA=1:DN=-1:DX=-1:SP=1:PR=-1:OBJ=Crystalwisp:MX=6:SB=0:RT=0:TO=0:KL=0:RK=0:CA=1:DN=-1:DX=-1:SP=1:PR=-1</Objects2>
  </Points>
  <Points>
    <Name>PrismOfLight#11</Name>
    <UniqueId>705e39cc-b2c7-4306-ade1-bdf9ca863796</UniqueId>
    <Map>Felucca</Map>
    <X>6470</X>
    <Y>96</Y>
    <Width>10</Width>
    <Height>10</Height>
    <CentreX>6475</CentreX>
    <CentreY>101</CentreY>
    <CentreZ>-44</CentreZ>
    <Range>5</Range>
    <MaxCount>5</MaxCount>
    <MinDelay>5</MinDelay>
    <MaxDelay>10</MaxDelay>
    <DelayInSec>False</DelayInSec>
    <Duration>0</Duration>
    <DespawnTime>0</DespawnTime>
    <ProximityRange>-1</ProximityRange>
    <ProximityTriggerSound>500</ProximityTriggerSound>
    <TriggerProbability>1</TriggerProbability>
    <InContainer>False</InContainer>
    <MinRefractory>0</MinRefractory>
    <MaxRefractory>0</MaxRefractory>
    <TODStart>0</TODStart>
    <TODEnd>0</TODEnd>
    <TODMode>0</TODMode>
    <KillReset>1</KillReset>
    <ExternalTriggering>False</ExternalTriggering>
    <SequentialSpawning>-1</SequentialSpawning>
    <AllowGhostTriggering>False</AllowGhostTriggering>
    <AllowNPCTriggering>False</AllowNPCTriggering>
    <SpawnOnTrigger>False</SpawnOnTrigger>
    <SmartSpawning>False</SmartSpawning>
    <Team>0</Team>
    <Amount>1</Amount>
    <IsGroup>False</IsGroup>
    <IsRunning>True</IsRunning>
    <IsHomeRangeRelative>False</IsHomeRangeRelative>
    <Objects2>ShadowWisp:MX=5:SB=0:RT=0:TO=0:KL=0:RK=0:CA=1:DN=-1:DX=-1:SP=1:PR=-1</Objects2>
  </Points>
  <Points>
    <Name>PrismOfLight#10</Name>
    <UniqueId>e16eb220-8114-44b5-981a-2dc10a58e160</UniqueId>
    <Map>Felucca</Map>
    <X>6503</X>
    <Y>180</Y>
    <Width>2</Width>
    <Height>2</Height>
    <CentreX>6504</CentreX>
    <CentreY>181</CentreY>
    <CentreZ>0</CentreZ>
    <Range>1</Range>
    <MaxCount>1</MaxCount>
    <MinDelay>5</MinDelay>
    <MaxDelay>10</MaxDelay>
    <DelayInSec>False</DelayInSec>
    <Duration>0</Duration>
    <DespawnTime>0</DespawnTime>
    <ProximityRange>-1</ProximityRange>
    <ProximityTriggerSound>500</ProximityTriggerSound>
    <TriggerProbability>1</TriggerProbability>
    <InContainer>False</InContainer>
    <MinRefractory>0</MinRefractory>
    <MaxRefractory>0</MaxRefractory>
    <TODStart>0</TODStart>
    <TODEnd>0</TODEnd>
    <TODMode>0</TODMode>
    <KillReset>1</KillReset>
    <ExternalTriggering>False</ExternalTriggering>
    <SequentialSpawning>-1</SequentialSpawning>
    <AllowGhostTriggering>False</AllowGhostTriggering>
    <AllowNPCTriggering>False</AllowNPCTriggering>
    <SpawnOnTrigger>False</SpawnOnTrigger>
    <SmartSpawning>False</SmartSpawning>
    <Team>0</Team>
    <Amount>1</Amount>
    <IsGroup>False</IsGroup>
    <IsRunning>True</IsRunning>
    <IsHomeRangeRelative>False</IsHomeRangeRelative>
    <Objects2>treasurelevel4:MX=1:SB=0:RT=0:TO=0:KL=0:RK=0:CA=1:DN=-1:DX=-1:SP=1:PR=-1</Objects2>
  </Points>
  <Points>
    <Name>PrismOfLight#9</Name>
    <UniqueId>4053415e-de3c-412b-a2b0-d69605a22094</UniqueId>
    <Map>Felucca</Map>
    <X>6568</X>
    <Y>85</Y>
    <Width>8</Width>
    <Height>8</Height>
    <CentreX>6572</CentreX>
    <CentreY>89</CentreY>
    <CentreZ>0</CentreZ>
    <Range>4</Range>
    <MaxCount>2</MaxCount>
    <MinDelay>5</MinDelay>
    <MaxDelay>10</MaxDelay>
    <DelayInSec>False</DelayInSec>
    <Duration>0</Duration>
    <DespawnTime>0</DespawnTime>
    <ProximityRange>-1</ProximityRange>
    <ProximityTriggerSound>500</ProximityTriggerSound>
    <TriggerProbability>1</TriggerProbability>
    <InContainer>False</InContainer>
    <MinRefractory>0</MinRefractory>
    <MaxRefractory>0</MaxRefractory>
    <TODStart>0</TODStart>
    <TODEnd>0</TODEnd>
    <TODMode>0</TODMode>
    <KillReset>1</KillReset>
    <ExternalTriggering>False</ExternalTriggering>
    <SequentialSpawning>-1</SequentialSpawning>
    <AllowGhostTriggering>False</AllowGhostTriggering>
    <AllowNPCTriggering>False</AllowNPCTriggering>
    <SpawnOnTrigger>False</SpawnOnTrigger>
    <SmartSpawning>False</SmartSpawning>
    <Team>0</Team>
    <Amount>1</Amount>
    <IsGroup>False</IsGroup>
    <IsRunning>True</IsRunning>
    <IsHomeRangeRelative>False</IsHomeRangeRelative>
    <Objects2>CrystalHydra:MX=2:SB=0:RT=0:TO=0:KL=0:RK=0:CA=1:DN=-1:DX=-1:SP=1:PR=-1</Objects2>
  </Points>
  <Points>
    <Name>PrismOfLight#8</Name>
    <UniqueId>83d4ebf2-5c05-4122-9d70-027b8d05aefd</UniqueId>
    <Map>Felucca</Map>
    <X>6543</X>
    <Y>87</Y>
    <Width>8</Width>
    <Height>8</Height>
    <CentreX>6547</CentreX>
    <CentreY>91</CentreY>
    <CentreZ>-10</CentreZ>
    <Range>4</Range>
    <MaxCount>1</MaxCount>
    <MinDelay>5</MinDelay>
    <MaxDelay>10</MaxDelay>
    <DelayInSec>False</DelayInSec>
    <Duration>0</Duration>
    <DespawnTime>0</DespawnTime>
    <ProximityRange>-1</ProximityRange>
    <ProximityTriggerSound>500</ProximityTriggerSound>
    <TriggerProbability>1</TriggerProbability>
    <InContainer>False</InContainer>
    <MinRefractory>0</MinRefractory>
    <MaxRefractory>0</MaxRefractory>
    <TODStart>0</TODStart>
    <TODEnd>0</TODEnd>
    <TODMode>0</TODMode>
    <KillReset>1</KillReset>
    <ExternalTriggering>False</ExternalTriggering>
    <SequentialSpawning>-1</SequentialSpawning>
    <AllowGhostTriggering>False</AllowGhostTriggering>
    <AllowNPCTriggering>False</AllowNPCTriggering>
    <SpawnOnTrigger>False</SpawnOnTrigger>
    <SmartSpawning>False</SmartSpawning>
    <Team>0</Team>
    <Amount>1</Amount>
    <IsGroup>False</IsGroup>
    <IsRunning>True</IsRunning>
    <IsHomeRangeRelative>False</IsHomeRangeRelative>
    <Objects2>CrystalDaemon:MX=1:SB=0:RT=0:TO=0:KL=0:RK=0:CA=1:DN=-1:DX=-1:SP=1:PR=-1</Objects2>
  </Points>
  <Points>
    <Name>PrismOfLight#7</Name>
    <UniqueId>68755d48-0d60-420f-a45a-c2ffc4cf6af5</UniqueId>
    <Map>Felucca</Map>
    <X>6532</X>
    <Y>75</Y>
    <Width>8</Width>
    <Height>8</Height>
    <CentreX>6536</CentreX>
    <CentreY>79</CentreY>
    <CentreZ>-10</CentreZ>
    <Range>4</Range>
    <MaxCount>1</MaxCount>
    <MinDelay>5</MinDelay>
    <MaxDelay>10</MaxDelay>
    <DelayInSec>False</DelayInSec>
    <Duration>0</Duration>
    <DespawnTime>0</DespawnTime>
    <ProximityRange>-1</ProximityRange>
    <ProximityTriggerSound>500</ProximityTriggerSound>
    <TriggerProbability>1</TriggerProbability>
    <InContainer>False</InContainer>
    <MinRefractory>0</MinRefractory>
    <MaxRefractory>0</MaxRefractory>
    <TODStart>0</TODStart>
    <TODEnd>0</TODEnd>
    <TODMode>0</TODMode>
    <KillReset>1</KillReset>
    <ExternalTriggering>False</ExternalTriggering>
    <SequentialSpawning>-1</SequentialSpawning>
    <AllowGhostTriggering>False</AllowGhostTriggering>
    <AllowNPCTriggering>False</AllowNPCTriggering>
    <SpawnOnTrigger>False</SpawnOnTrigger>
    <SmartSpawning>False</SmartSpawning>
    <Team>0</Team>
    <Amount>1</Amount>
    <IsGroup>False</IsGroup>
    <IsRunning>True</IsRunning>
    <IsHomeRangeRelative>False</IsHomeRangeRelative>
    <Objects2>CrystalDaemon:MX=1:SB=0:RT=0:TO=0:KL=0:RK=0:CA=1:DN=-1:DX=-1:SP=1:PR=-1</Objects2>
  </Points>
  <Points>
    <Name>PrismOfLight#6</Name>
    <UniqueId>1aad30d1-f232-40da-8655-b9ccc7ce5607</UniqueId>
    <Map>Felucca</Map>
    <X>6505</X>
    <Y>172</Y>
    <Width>8</Width>
    <Height>8</Height>
    <CentreX>6509</CentreX>
    <CentreY>176</CentreY>
    <CentreZ>0</CentreZ>
    <Range>4</Range>
    <MaxCount>2</MaxCount>
    <MinDelay>5</MinDelay>
    <MaxDelay>10</MaxDelay>
    <DelayInSec>False</DelayInSec>
    <Duration>0</Duration>
    <DespawnTime>0</DespawnTime>
    <ProximityRange>-1</ProximityRange>
    <ProximityTriggerSound>500</ProximityTriggerSound>
    <TriggerProbability>1</TriggerProbability>
    <InContainer>False</InContainer>
    <MinRefractory>0</MinRefractory>
    <MaxRefractory>0</MaxRefractory>
    <TODStart>0</TODStart>
    <TODEnd>0</TODEnd>
    <TODMode>0</TODMode>
    <KillReset>1</KillReset>
    <ExternalTriggering>False</ExternalTriggering>
    <SequentialSpawning>-1</SequentialSpawning>
    <AllowGhostTriggering>False</AllowGhostTriggering>
    <AllowNPCTriggering>False</AllowNPCTriggering>
    <SpawnOnTrigger>False</SpawnOnTrigger>
    <SmartSpawning>False</SmartSpawning>
    <Team>0</Team>
    <Amount>1</Amount>
    <IsGroup>False</IsGroup>
    <IsRunning>True</IsRunning>
    <IsHomeRangeRelative>False</IsHomeRangeRelative>
    <Objects2>UnfrozenMummy:MX=2:SB=0:RT=0:TO=0:KL=0:RK=0:CA=1:DN=-1:DX=-1:SP=1:PR=-1</Objects2>
  </Points>
  <Points>
    <Name>PrismOfLight#5</Name>
    <UniqueId>2768da48-a6fd-4eb8-8836-91d62a2d5ac4</UniqueId>
    <Map>Felucca</Map>
    <X>6572</X>
    <Y>87</Y>
    <Width>8</Width>
    <Height>8</Height>
    <CentreX>6576</CentreX>
    <CentreY>91</CentreY>
    <CentreZ>0</CentreZ>
    <Range>4</Range>
    <MaxCount>2</MaxCount>
    <MinDelay>5</MinDelay>
    <MaxDelay>10</MaxDelay>
    <DelayInSec>False</DelayInSec>
    <Duration>0</Duration>
    <DespawnTime>0</DespawnTime>
    <ProximityRange>-1</ProximityRange>
    <ProximityTriggerSound>500</ProximityTriggerSound>
    <TriggerProbability>1</TriggerProbability>
    <InContainer>False</InContainer>
    <MinRefractory>0</MinRefractory>
    <MaxRefractory>0</MaxRefractory>
    <TODStart>0</TODStart>
    <TODEnd>0</TODEnd>
    <TODMode>0</TODMode>
    <KillReset>1</KillReset>
    <ExternalTriggering>False</ExternalTriggering>
    <SequentialSpawning>-1</SequentialSpawning>
    <AllowGhostTriggering>False</AllowGhostTriggering>
    <AllowNPCTriggering>False</AllowNPCTriggering>
    <SpawnOnTrigger>False</SpawnOnTrigger>
    <SmartSpawning>False</SmartSpawning>
    <Team>0</Team>
    <Amount>1</Amount>
    <IsGroup>False</IsGroup>
    <IsRunning>True</IsRunning>
    <IsHomeRangeRelative>False</IsHomeRangeRelative>
    <Objects2>CrystalSeaSerpent:MX=2:SB=0:RT=0:TO=0:KL=0:RK=0:CA=1:DN=-1:DX=-1:SP=1:PR=-1</Objects2>
  </Points>
  <Points>
    <Name>PrismOfLight#4</Name>
    <UniqueId>d58760e0-22a6-4575-9cc1-c1463a0f4c65</UniqueId>
    <Map>Felucca</Map>
    <X>6526</X>
    <Y>135</Y>
    <Width>8</Width>
    <Height>8</Height>
    <CentreX>6530</CentreX>
    <CentreY>139</CentreY>
    <CentreZ>-20</CentreZ>
    <Range>4</Range>
    <MaxCount>1</MaxCount>
    <MinDelay>5</MinDelay>
    <MaxDelay>10</MaxDelay>
    <DelayInSec>False</DelayInSec>
    <Duration>0</Duration>
    <DespawnTime>0</DespawnTime>
    <ProximityRange>-1</ProximityRange>
    <ProximityTriggerSound>500</ProximityTriggerSound>
    <TriggerProbability>1</TriggerProbability>
    <InContainer>False</InContainer>
    <MinRefractory>0</MinRefractory>
    <MaxRefractory>0</MaxRefractory>
    <TODStart>0</TODStart>
    <TODEnd>0</TODEnd>
    <TODMode>0</TODMode>
    <KillReset>1</KillReset>
    <ExternalTriggering>False</ExternalTriggering>
    <SequentialSpawning>-1</SequentialSpawning>
    <AllowGhostTriggering>False</AllowGhostTriggering>
    <AllowNPCTriggering>False</AllowNPCTriggering>
    <SpawnOnTrigger>False</SpawnOnTrigger>
    <SmartSpawning>False</SmartSpawning>
    <Team>0</Team>
    <Amount>1</Amount>
    <IsGroup>False</IsGroup>
    <IsRunning>True</IsRunning>
    <IsHomeRangeRelative>False</IsHomeRangeRelative>
    <Objects2>wisp:MX=1:SB=0:RT=0:TO=0:KL=0:RK=0:CA=1:DN=-1:DX=-1:SP=1:PR=-1</Objects2>
  </Points>
  <Points>
    <Name>PrismOfLight#3</Name>
    <UniqueId>a8de00cb-6b17-4025-85a2-a7d0901aedde</UniqueId>
    <Map>Felucca</Map>
    <X>6517</X>
    <Y>135</Y>
    <Width>8</Width>
    <Height>8</Height>
    <CentreX>6521</CentreX>
    <CentreY>139</CentreY>
    <CentreZ>-20</CentreZ>
    <Range>4</Range>
    <MaxCount>1</MaxCount>
    <MinDelay>5</MinDelay>
    <MaxDelay>10</MaxDelay>
    <DelayInSec>False</DelayInSec>
    <Duration>0</Duration>
    <DespawnTime>0</DespawnTime>
    <ProximityRange>-1</ProximityRange>
    <ProximityTriggerSound>500</ProximityTriggerSound>
    <TriggerProbability>1</TriggerProbability>
    <InContainer>False</InContainer>
    <MinRefractory>0</MinRefractory>
    <MaxRefractory>0</MaxRefractory>
    <TODStart>0</TODStart>
    <TODEnd>0</TODEnd>
    <TODMode>0</TODMode>
    <KillReset>1</KillReset>
    <ExternalTriggering>False</ExternalTriggering>
    <SequentialSpawning>-1</SequentialSpawning>
    <AllowGhostTriggering>False</AllowGhostTriggering>
    <AllowNPCTriggering>False</AllowNPCTriggering>
    <SpawnOnTrigger>False</SpawnOnTrigger>
    <SmartSpawning>False</SmartSpawning>
    <Team>0</Team>
    <Amount>1</Amount>
    <IsGroup>False</IsGroup>
    <IsRunning>True</IsRunning>
    <IsHomeRangeRelative>False</IsHomeRangeRelative>
    <Objects2>wisp:MX=1:SB=0:RT=0:TO=0:KL=0:RK=0:CA=1:DN=-1:DX=-1:SP=1:PR=-1</Objects2>
  </Points>
  <Points>
    <Name>PrismOfLight#2</Name>
    <UniqueId>a0e78e01-f067-47d2-b94d-a6285c019289</UniqueId>
    <Map>Felucca</Map>
    <X>6537</X>
    <Y>140</Y>
    <Width>30</Width>
    <Height>30</Height>
    <CentreX>6552</CentreX>
    <CentreY>155</CentreY>
    <CentreZ>0</CentreZ>
    <Range>15</Range>
    <MaxCount>6</MaxCount>
    <MinDelay>5</MinDelay>
    <MaxDelay>10</MaxDelay>
    <DelayInSec>False</DelayInSec>
    <Duration>0</Duration>
    <DespawnTime>0</DespawnTime>
    <ProximityRange>-1</ProximityRange>
    <ProximityTriggerSound>500</ProximityTriggerSound>
    <TriggerProbability>1</TriggerProbability>
    <InContainer>False</InContainer>
    <MinRefractory>0</MinRefractory>
    <MaxRefractory>0</MaxRefractory>
    <TODStart>0</TODStart>
    <TODEnd>0</TODEnd>
    <TODMode>0</TODMode>
    <KillReset>1</KillReset>
    <ExternalTriggering>False</ExternalTriggering>
    <SequentialSpawning>-1</SequentialSpawning>
    <AllowGhostTriggering>False</AllowGhostTriggering>
    <AllowNPCTriggering>False</AllowNPCTriggering>
    <SpawnOnTrigger>False</SpawnOnTrigger>
    <SmartSpawning>False</SmartSpawning>
    <Team>0</Team>
    <Amount>1</Amount>
    <IsGroup>False</IsGroup>
    <IsRunning>True</IsRunning>
    <IsHomeRangeRelative>False</IsHomeRangeRelative>
    <Objects2>wisp:MX=5:SB=0:RT=0:TO=0:KL=0:RK=0:CA=1:DN=-1:DX=-1:SP=1:PR=-1:OBJ=CrystalWisp:MX=5:SB=0:RT=0:TO=0:KL=0:RK=0:CA=1:DN=-1:DX=-1:SP=1:PR=-1:OBJ=treasurelevel2:MX=5:SB=0:RT=0:TO=0:KL=0:RK=0:CA=1:DN=-1:DX=-1:SP=1:PR=-1</Objects2>
  </Points>
  <Points>
    <Name>PrismOfLight#1</Name>
    <UniqueId>930f269b-aa63-44b4-91b1-328e4496bd08</UniqueId>
    <Map>Felucca</Map>
    <X>6470</X>
    <Y>70</Y>
    <Width>8</Width>
    <Height>8</Height>
    <CentreX>6474</CentreX>
    <CentreY>74</CentreY>
    <CentreZ>-34</CentreZ>
    <Range>4</Range>
    <MaxCount>9</MaxCount>
    <MinDelay>5</MinDelay>
    <MaxDelay>10</MaxDelay>
    <DelayInSec>False</DelayInSec>
    <Duration>0</Duration>
    <DespawnTime>0</DespawnTime>
    <ProximityRange>-1</ProximityRange>
    <ProximityTriggerSound>500</ProximityTriggerSound>
    <TriggerProbability>1</TriggerProbability>
    <InContainer>False</InContainer>
    <MinRefractory>0</MinRefractory>
    <MaxRefractory>0</MaxRefractory>
    <TODStart>0</TODStart>
    <TODEnd>0</TODEnd>
    <TODMode>0</TODMode>
    <KillReset>1</KillReset>
    <ExternalTriggering>False</ExternalTriggering>
    <SequentialSpawning>-1</SequentialSpawning>
    <AllowGhostTriggering>False</AllowGhostTriggering>
    <AllowNPCTriggering>False</AllowNPCTriggering>
    <SpawnOnTrigger>False</SpawnOnTrigger>
    <SmartSpawning>False</SmartSpawning>
    <Team>0</Team>
    <Amount>1</Amount>
    <IsGroup>False</IsGroup>
    <IsRunning>True</IsRunning>
    <IsHomeRangeRelative>False</IsHomeRangeRelative>
    <Objects2>Rat:MX=9:SB=0:RT=0:TO=0:KL=0:RK=0:CA=1:DN=-1:DX=-1:SP=1:PR=-1:OBJ=Icesnake:MX=9:SB=0:RT=0:TO=0:KL=0:RK=0:CA=1:DN=-1:DX=-1:SP=1:PR=-1</Objects2>
  </Points>
  <Points>
    <Name>PrismOfLight#0</Name>
    <UniqueId>5254a4d5-7583-4ebd-baf8-6902ea373c1a</UniqueId>
    <Map>Felucca</Map>
    <X>6545</X>
    <Y>149</Y>
    <Width>16</Width>
    <Height>16</Height>
    <CentreX>6553</CentreX>
    <CentreY>157</CentreY>
    <CentreZ>0</CentreZ>
    <Range>8</Range>
    <MaxCount>3</MaxCount>
    <MinDelay>5</MinDelay>
    <MaxDelay>10</MaxDelay>
    <DelayInSec>False</DelayInSec>
    <Duration>0</Duration>
    <DespawnTime>0</DespawnTime>
    <ProximityRange>-1</ProximityRange>
    <ProximityTriggerSound>500</ProximityTriggerSound>
    <TriggerProbability>1</TriggerProbability>
    <InContainer>False</InContainer>
    <MinRefractory>0</MinRefractory>
    <MaxRefractory>0</MaxRefractory>
    <TODStart>0</TODStart>
    <TODEnd>0</TODEnd>
    <TODMode>0</TODMode>
    <KillReset>1</KillReset>
    <ExternalTriggering>False</ExternalTriggering>
    <SequentialSpawning>-1</SequentialSpawning>
    <AllowGhostTriggering>False</AllowGhostTriggering>
    <AllowNPCTriggering>False</AllowNPCTriggering>
    <SpawnOnTrigger>False</SpawnOnTrigger>
    <SmartSpawning>False</SmartSpawning>
    <Team>0</Team>
    <Amount>1</Amount>
    <IsGroup>False</IsGroup>
    <IsRunning>True</IsRunning>
    <IsHomeRangeRelative>False</IsHomeRangeRelative>
    <Objects2>CrystalLatticeSeeker:MX=3:SB=0:RT=0:TO=0:KL=0:RK=0:CA=1:DN=-1:DX=-1:SP=1:PR=-1</Objects2>
  </Points>
</Spawns>