<?xml version="1.0" standalone="yes"?>
<Spawns>
  <Points>
    <Name>Harmon's Quest #3</Name>
    <UniqueId>7b7ad650-6c8a-4111-a9b0-915a9123228c</UniqueId>
    <Map>Felucca</Map>
    <X>1497</X>
    <Y>1628</Y>
    <Width>10</Width>
    <Height>10</Height>
    <CentreX>1502</CentreX>
    <CentreY>1633</CentreY>
    <CentreZ>10</CentreZ>
    <Range>5</Range>
    <MaxCount>6</MaxCount>
    <MinDelay>0</MinDelay>
    <MaxDelay>0</MaxDelay>
    <DelayInSec>False</DelayInSec>
    <Duration>0</Duration>
    <DespawnTime>0</DespawnTime>
    <ProximityRange>3</ProximityRange>
    <ProximityTriggerSound>500</ProximityTriggerSound>
    <ItemTriggerName>Harmon's Quest,3</ItemTriggerName>
    <TriggerProbability>1</TriggerProbability>
    <InContainer>False</InContainer>
    <ContainerX>0</ContainerX>
    <ContainerY>0</ContainerY>
    <ContainerZ>0</ContainerZ>
    <MinRefractory>0</MinRefractory>
    <MaxRefractory>0</MaxRefractory>
    <TODStart>0</TODStart>
    <TODEnd>0</TODEnd>
    <TODMode>0</TODMode>
    <KillReset>1</KillReset>
    <ExternalTriggering>False</ExternalTriggering>
    <SequentialSpawning>-1</SequentialSpawning>
    <AllowGhostTriggering>False</AllowGhostTriggering>
    <SmartSpawning>False</SmartSpawning>
    <Team>0</Team>
    <Amount>1</Amount>
    <IsGroup>False</IsGroup>
    <IsRunning>True</IsRunning>
    <IsHomeRangeRelative>True</IsHomeRangeRelative>
    <Objects2>SETONTRIGMOB/ATTACH/xmladdvirtue,Compassion,5:MX=1:SB=1:RT=0:TO=0:KL=0:RK=0:CA=1:DN=-1:DX=-1:OBJ=TAKE/Harmon's note:MX=1:SB=1:RT=0:TO=0:KL=0:RK=0:CA=1:DN=-1:DX=-1:OBJ=SETONSPAWN,Harmon's Quest #1,1/MSG/*sob* oh no... it cant be..:MX=1:SB=1:RT=0:TO=0:KL=0:RK=0:CA=1:DN=-1:DX=-1:OBJ=SETONTRIGMOB/MSG/you hear him quietly mourning:MX=1:SB=1:RT=0:TO=0:KL=0:RK=0:CA=1:DN=-1:DX=-1:OBJ=SETONTRIGMOB/ATTACH/XmlQuestAttachment,Harmon's Quest,1440:MX=1:SB=1:RT=0:TO=0:KL=0:RK=0:CA=1:DN=-1:DX=-1:OBJ=TAKE/Harmon's Quest:MX=1:SB=1:RT=0:TO=0:KL=0:RK=0:CA=1:DN=-1:DX=-1</Objects2>
  </Points>
  <Points>
    <Name>Harmon's Quest #4</Name>
    <UniqueId>2bcc4c2f-b005-4b85-ab37-bb8a0b6e95b6</UniqueId>
    <Map>Felucca</Map>
    <X>6093</X>
    <Y>37</Y>
    <Width>10</Width>
    <Height>10</Height>
    <CentreX>6098</CentreX>
    <CentreY>42</CentreY>
    <CentreZ>22</CentreZ>
    <Range>5</Range>
    <MaxCount>2</MaxCount>
    <MinDelay>5</MinDelay>
    <MaxDelay>5</MaxDelay>
    <DelayInSec>True</DelayInSec>
    <Duration>0</Duration>
    <DespawnTime>0</DespawnTime>
    <ProximityRange>10</ProximityRange>
    <ProximityTriggerSound>500</ProximityTriggerSound>
    <ItemTriggerName>Harmon's Quest</ItemTriggerName>
    <NoItemTriggerName>Harmon's Quest,1</NoItemTriggerName>
    <TriggerProbability>1</TriggerProbability>
    <InContainer>False</InContainer>
    <ContainerX>0</ContainerX>
    <ContainerY>0</ContainerY>
    <ContainerZ>0</ContainerZ>
    <MinRefractory>0</MinRefractory>
    <MaxRefractory>0</MaxRefractory>
    <TODStart>0</TODStart>
    <TODEnd>0</TODEnd>
    <TODMode>0</TODMode>
    <KillReset>1</KillReset>
    <ExternalTriggering>False</ExternalTriggering>
    <SequentialSpawning>-1</SequentialSpawning>
    <AllowGhostTriggering>False</AllowGhostTriggering>
    <SmartSpawning>False</SmartSpawning>
    <Team>0</Team>
    <Amount>1</Amount>
    <IsGroup>False</IsGroup>
    <IsRunning>True</IsRunning>
    <IsHomeRangeRelative>True</IsHomeRangeRelative>
    <Objects2>Balron/hue/500/name/Oberon the Wicked/ADD/&lt;simplenote/size/3/name/Harmon's note/notestring/Father, if you are reading this it means that I shall not return.  I have been lost in these hellish depths for days, and now I hear evil approaching. I fear there is no escape. I should never have left in anger. I was wrong. I wanted you to know that I am sorry.&gt;:MX=1:SB=1:RT=0:TO=0:KL=0:RK=0:CA=1:DN=-1:DX=-1:OBJ=SETONCARRIED,Harmon's Quest/Objective2/KILLNAMED,Oberon the Wicked/Completed1/true/Objective3/GIVENAMED,Harmon,Harmon's note/Description3/Return the note to Harmon:MX=1:SB=1:RT=0:TO=0:KL=0:RK=0:CA=1:DN=-1:DX=-1</Objects2>
  </Points>
  <Points>
    <Name>Harmon's Quest #2</Name>
    <UniqueId>5101fe6f-d6d1-4175-9e2c-f6351ce64de3</UniqueId>
    <Map>Felucca</Map>
    <X>1496</X>
    <Y>1628</Y>
    <Width>10</Width>
    <Height>10</Height>
    <CentreX>1501</CentreX>
    <CentreY>1633</CentreY>
    <CentreZ>10</CentreZ>
    <Range>5</Range>
    <MaxCount>24</MaxCount>
    <MinDelay>1</MinDelay>
    <MaxDelay>1</MaxDelay>
    <DelayInSec>True</DelayInSec>
    <Duration>0</Duration>
    <DespawnTime>0</DespawnTime>
    <ProximityRange>5</ProximityRange>
    <ProximityTriggerSound>784</ProximityTriggerSound>
    <NoItemTriggerName>Harmon's Quest</NoItemTriggerName>
    <TriggerProbability>1</TriggerProbability>
    <SpeechTrigger>Hail</SpeechTrigger>
    <InContainer>False</InContainer>
    <ContainerX>0</ContainerX>
    <ContainerY>0</ContainerY>
    <ContainerZ>0</ContainerZ>
    <MinRefractory>0</MinRefractory>
    <MaxRefractory>0</MaxRefractory>
    <TODStart>0</TODStart>
    <TODEnd>0</TODEnd>
    <TODMode>0</TODMode>
    <KillReset>1</KillReset>
    <ExternalTriggering>False</ExternalTriggering>
    <SequentialSpawning>1</SequentialSpawning>
    <AllowGhostTriggering>False</AllowGhostTriggering>
    <SmartSpawning>False</SmartSpawning>
    <Team>0</Team>
    <Amount>1</Amount>
    <IsGroup>False</IsGroup>
    <IsRunning>True</IsRunning>
    <IsHomeRangeRelative>True</IsHomeRangeRelative>
    <Objects2>SETONTHIS/freerun/true:MX=1:SB=1:RT=0:TO=0:KL=0:RK=0:CA=1:DN=-1:DX=-1:OBJ=SETONTHIS/gumpstate/(-null-)/:MX=1:SB=2:RT=0:TO=0:KL=0:RK=0:CA=1:DN=-1:DX=-1:OBJ=GUMP,Harmon,4/You see a sad old man holding a small tin cup. His hands are trembling and he mumbles something incoherently.  You come closer.;Help him out with a few coins as a responsible citizen of Britannia;help;Kick him and tell him to move along;kick;Distract him and pick his pockets;steal;Ask him to repeat what he said;ask:MX=1:SB=2:RT=0:TO=0:KL=0:RK=0:CA=1:DN=-1:DX=-1:OBJ=WAITUNTIL,0,1/gumpstate!(-null-)/44:MX=1:SB=2:RT=0:TO=0:KL=0:RK=0:CA=1:DN=-1:DX=-1:OBJ=SETONTHIS/gumpstate/(-null-):MX=1:SB=3:RT=0:TO=0:KL=0:RK=0:CA=1:DN=-1:DX=-1:OBJ=GUMP,Harmon's Quest,3/Please find my son...:MX=1:SB=3:RT=0:TO=0:KL=0:RK=0:CA=1:DN=-1:DX=-1:OBJ=WAITUNTIL,0,1/gumpstate!(-null-)/66:MX=1:SB=3:RT=0:TO=0:KL=0:RK=0:CA=1:DN=-1:DX=-1:OBJ=SETONTHIS/proximityactivated/false:MX=1:SB=33:RT=0:TO=0:KL=0:RK=0:CA=1:DN=-1:DX=-1:OBJ=SETONTHIS/freerun/false:MX=1:SB=33:RT=0:TO=0:KL=0:RK=0:CA=1:DN=-1:DX=-1:OBJ=GOTO/1/1:MX=1:SB=33:RT=0:TO=0:KL=0:RK=0:CA=1:DN=-1:DX=-1:OBJ=IF/gumpstate="steal"/88:MX=1:SB=44:RT=0:TO=0:KL=0:RK=0:CA=1:DN=-1:DX=-1:OBJ=IF/gumpstate="help"/90:MX=1:SB=44:RT=0:TO=0:KL=0:RK=0:CA=1:DN=-1:DX=-1:OBJ=IF/gumpstate="kick"/95:MX=1:SB=44:RT=0:TO=0:KL=0:RK=0:CA=1:DN=-1:DX=-1:OBJ=IF/gumpstate="accept"/77/33:MX=1:SB=66:RT=0:TO=0:KL=0:RK=0:CA=1:DN=-1:DX=-1:OBJ=GIVE/&lt;questholder/name/Harmon's Quest/titlestring/Locate Harmon's son./objective1/Search the depths of Hythloth.:MX=1:SB=77:RT=0:TO=0:KL=0:RK=0:CA=1:DN=-1:DX=-1:OBJ=SETONTRIGMOB/MSG/*Receives Harmon's Quest*:MX=1:SB=77:RT=0:TO=0:KL=0:RK=0:CA=1:DN=-1:DX=-1:OBJ=SOUND,61:MX=1:SB=77:RT=0:TO=0:KL=0:RK=0:CA=1:DN=-1:DX=-1:OBJ=SENDMSG/He is penniless...:MX=1:SB=88:RT=0:TO=0:KL=0:RK=0:CA=1:DN=-1:DX=-1:OBJ=GOTO/33:MX=1:SB=88:RT=0:TO=0:KL=0:RK=0:CA=1:DN=-1:DX=-1:OBJ=SENDMSG/He shakes his head and refuses your money..:MX=1:SB=90:RT=0:TO=0:KL=0:RK=0:CA=1:DN=-1:DX=-1:OBJ=GOTO/33/:MX=1:SB=90:RT=0:TO=0:KL=0:RK=0:CA=1:DN=-1:DX=-1:OBJ=SENDMSG/He simply continues sobbing..:MX=1:SB=95:RT=0:TO=0:KL=0:RK=0:CA=1:DN=-1:DX=-1:OBJ=GOTO/33/1:MX=1:SB=95:RT=0:TO=0:KL=0:RK=0:CA=1:DN=-1:DX=-1</Objects2>
  </Points>
  <Points>
    <Name>Harmon's Quest #1</Name>
    <UniqueId>1d774243-09b8-4c2c-a607-553513104acb</UniqueId>
    <Map>Felucca</Map>
    <X>1501</X>
    <Y>1634</Y>
    <Width>0</Width>
    <Height>0</Height>
    <CentreX>1501</CentreX>
    <CentreY>1634</CentreY>
    <CentreZ>10</CentreZ>
    <Range>0</Range>
    <MaxCount>1</MaxCount>
    <MinDelay>5</MinDelay>
    <MaxDelay>10</MaxDelay>
    <DelayInSec>False</DelayInSec>
    <Duration>0</Duration>
    <DespawnTime>0</DespawnTime>
    <ProximityRange>-1</ProximityRange>
    <ProximityTriggerSound>500</ProximityTriggerSound>
    <TriggerProbability>1</TriggerProbability>
    <InContainer>False</InContainer>
    <ContainerX>0</ContainerX>
    <ContainerY>0</ContainerY>
    <ContainerZ>0</ContainerZ>
    <MinRefractory>0</MinRefractory>
    <MaxRefractory>0</MaxRefractory>
    <TODStart>0</TODStart>
    <TODEnd>0</TODEnd>
    <TODMode>0</TODMode>
    <KillReset>1</KillReset>
    <ExternalTriggering>False</ExternalTriggering>
    <SequentialSpawning>-1</SequentialSpawning>
    <AllowGhostTriggering>False</AllowGhostTriggering>
    <SmartSpawning>False</SmartSpawning>
    <Team>0</Team>
    <Amount>1</Amount>
    <IsGroup>False</IsGroup>
    <IsRunning>True</IsRunning>
    <IsHomeRangeRelative>True</IsHomeRangeRelative>
    <Objects2>xmlquestnpc,0/name/Harmon:MX=1:SB=1:RT=0:TO=0:KL=0:RK=0:CA=1:DN=-1:DX=-1</Objects2>
  </Points>
</Spawns>